dbcompanion/__init__.py
dbcompanion/report.py
dbcompanion/step.py
dbcompanion/utils/__init__.py
dbcompanion/utils/code_utils.py
dbcompanion/utils/db_utils.py
dbcompanion/utils/oai_utils.py
dbcompanion/utils/prompt.py
dbcompanion-0.0.8.dist-info/METADATA
dbcompanion-0.0.8.dist-info/WHEEL
dbcompanion-0.0.8.dist-info/licenses/LICENSE
dbcompanion-0.0.8.dist-info/RECORD
