Metadata-Version: 2.1
Name: dbcompanion
Version: 0.0.8
Summary: Talk with your database
Project-URL: Code, https://github.com/Ransaka/bdcompanion
Project-URL: Docs, https://github.com/Ransaka/bdcompanion
Author-email: Ransaka <ransaka.ravihara@gmail.com>
License: MIT License
License-File: LICENSE
Keywords: chatgpt,mysql,python,sql
Classifier: License :: OSI Approved :: MIT License
Classifier: Programming Language :: Python :: 3.9
Classifier: Programming Language :: Python :: 3.10
Classifier: Programming Language :: Python :: 3.11
Classifier: Topic :: Scientific/Engineering :: Artificial Intelligence
Requires-Python: <3.12,>=3.9.7
Requires-Dist: markdown>=3.5.2
Requires-Dist: openai
Requires-Dist: pandas>=1.5.1
Requires-Dist: pydantic-settings>=2
Requires-Dist: pydantic>=2
Requires-Dist: pymysql>=1.1.0
Requires-Dist: tqdm>=4.66.1
